google/cloud/assuredworkloads/__init__.py
google/cloud/assuredworkloads/gapic_version.py
google/cloud/assuredworkloads/py.typed
google/cloud/assuredworkloads_v1/__init__.py
google/cloud/assuredworkloads_v1/gapic_metadata.json
google/cloud/assuredworkloads_v1/gapic_version.py
google/cloud/assuredworkloads_v1/py.typed
google/cloud/assuredworkloads_v1/services/__init__.py
google/cloud/assuredworkloads_v1/services/assured_workloads_service/__init__.py
google/cloud/assuredworkloads_v1/services/assured_workloads_service/async_client.py
google/cloud/assuredworkloads_v1/services/assured_workloads_service/client.py
google/cloud/assuredworkloads_v1/services/assured_workloads_service/pagers.py
google/cloud/assuredworkloads_v1/services/assured_workloads_service/transports/__init__.py
google/cloud/assuredworkloads_v1/services/assured_workloads_service/transports/base.py
google/cloud/assuredworkloads_v1/services/assured_workloads_service/transports/grpc.py
google/cloud/assuredworkloads_v1/services/assured_workloads_service/transports/grpc_asyncio.py
google/cloud/assuredworkloads_v1/services/assured_workloads_service/transports/rest.py
google/cloud/assuredworkloads_v1/services/assured_workloads_service/transports/rest_base.py
google/cloud/assuredworkloads_v1/types/__init__.py
google/cloud/assuredworkloads_v1/types/assuredworkloads.py
google/cloud/assuredworkloads_v1beta1/__init__.py
google/cloud/assuredworkloads_v1beta1/gapic_metadata.json
google/cloud/assuredworkloads_v1beta1/gapic_version.py
google/cloud/assuredworkloads_v1beta1/py.typed
google/cloud/assuredworkloads_v1beta1/services/__init__.py
google/cloud/assuredworkloads_v1beta1/services/assured_workloads_service/__init__.py
google/cloud/assuredworkloads_v1beta1/services/assured_workloads_service/async_client.py
google/cloud/assuredworkloads_v1beta1/services/assured_workloads_service/client.py
google/cloud/assuredworkloads_v1beta1/services/assured_workloads_service/pagers.py
google_cloud_assured_workloads-2.2.0.dist-info/licenses/LICENSE
google_cloud_assured_workloads-2.2.0.dist-info/METADATA
google_cloud_assured_workloads-2.2.0.dist-info/WHEEL
google_cloud_assured_workloads-2.2.0.dist-info/top_level.txt
google_cloud_assured_workloads-2.2.0.dist-info/RECORD
